README.rst
setup.py
src/passless/ImNotSpider.py
src/passless/__init__.py
src/passless/__main__.py
src/passless/get_adblk.py
src/passless/get_server.py
src/passless/gvars.py
src/passless/runtime.py
src/passless/utils.py
src/passless.egg-info/PKG-INFO
src/passless.egg-info/SOURCES.txt
src/passless.egg-info/dependency_links.txt
src/passless.egg-info/entry_points.txt
src/passless.egg-info/requires.txt
src/passless.egg-info/top_level.txt
src/passless/proxies/__init__.py
src/passless/proxies/base/__init__.py
src/passless/proxies/base/server.py
src/passless/proxies/http/__init__.py
src/passless/proxies/http/server.py
src/passless/proxies/passless/__init__.py
src/passless/proxies/passless/client.py
src/passless/proxies/passless/shadowsockssocket.py
src/passless/proxies/socks/__init__.py
src/passless/proxies/socks/server.py