Metadata-Version: 1.2
Name: passless
Version: 0.0.1.dev1
Summary: A toolkit for setting up a security layer to protect private services
Home-page: http://passless.pyforce.com
Author: Wilhelm Shen
Author-email: wilhelmshen@pyforce.com
License: MIT
Keywords: gevent asynchronous socks
Platform: UNKNOWN
Classifier: License :: OSI Approved :: MIT License
Classifier: Programming Language :: Python :: 3.6
Classifier: Programming Language :: Python :: 3.7
Classifier: Programming Language :: Python :: 3.8
Classifier: Programming Language :: Python :: 3.9
Classifier: Programming Language :: Python :: Implementation :: CPython
Classifier: Operating System :: POSIX
Classifier: Topic :: Internet
Classifier: Topic :: Software Development :: Libraries :: Python Modules
Classifier: Intended Audience :: Developers
Classifier: Development Status :: 4 - Beta
Requires-Python: >=3.6
